{"version":3,"start_time":1633805157.900036,"game_started":true,"end_time":1633805535.959378,"game_ended":true,"flight_start":[11.0,4102.2656],"flight_end":[4597.0,731.16455],"last_gas_center":[2123.2979,1120.1238],"last_gas_radius":88.0,"players":[{"local_player":false,"ranking":1,"jump_position":[2092.173,2572.4238],"jump_time":1633805183.2256331,"touchdown_position":[2090.0,1495.3334],"touchdown_time":1633805200.1722262,"death_position":[0.0,0.0],"death_time":0.0,"died_in_gas":false,"last_in_flight":false,"last_is_parachuting":false,"last_is_dead":false},{"local_player":false,"ranking":2,"jump_position":[3941.2395,1213.2024],"jump_time":1633805205.7342281,"touchdown_position":[4170.5,1367.6666],"touchdown_time":1633805214.3098521,"death_position":[2110.0403,1145.4937],"death_time":1633805535.9432147,"died_in_gas":false,"last_in_flight":false,"last_is_parachuting":false,"last_is_dead":true},{"local_player":false,"ranking":3,"jump_position":[1625.1157,2915.7502],"jump_time":1633805177.5397747,"touchdown_position":[1992.6666,3182.5],"touchdown_time":1633805192.0699642,"death_position":[2199.3333,1051.0],"death_time":1633805523.4090703,"died_in_gas":false,"last_in_flight":false,"last_is_parachuting":false,"last_is_dead":true},{"local_player":false,"ranking":4,"jump_position":[275.8941,3907.545],"jump_time":1633805161.1398134,"touchdown_position":[482.83334,3921.5],"touchdown_time":1633805168.44571,"death_position":[2037.1278,1136.4562],"death_time":1633805517.428525,"died_in_gas":false,"last_in_flight":false,"last_is_parachuting":false,"last_is_dead":true},{"local_player":false,"ranking":5,"jump_position":[1515.8711,2996.0547],"jump_time":1633805176.2168264,"touchdown_position":[2032.3138,2961.1125],"touchdown_time":1633805187.2833378,"death_position":[2253.8406,1073.1959],"death_time":1633805505.7909472,"died_in_gas":false,"last_in_flight":false,"last_is_parachuting":false,"last_is_dead":true},{"local_player":false,"ranking":6,"jump_position":[3343.0994,1652.8864],"jump_time":1633805198.4569178,"touchdown_position":[3247.5,1848.3334],"touchdown_time":1633805209.4740815,"death_position":[2058.8948,1015.5],"death_time":1633805505.5557709,"died_in_gas":false,"last_in_flight":false,"last_is_parachuting":false,"last_is_dead":true},{"local_player":false,"ranking":7,"jump_position":[1712.5161,2851.5032],"jump_time":1633805178.6154153,"touchdown_position":[1725.0,2621.0],"touchdown_time":1633805186.6491992,"death_position":[2040.1666,1132.6666],"death_time":1633805504.9904206,"died_in_gas":false,"last_in_flight":false,"last_is_parachuting":false,"last_is_dead":true},{"local_player":false,"ranking":8,"jump_position":[2581.0723,2213.0417],"jump_time":1633805189.172168,"touchdown_position":[2397.8333,1894.1666],"touchdown_time":1633805206.1244779,"death_position":[1812.5334,802.87714],"death_time":1633805465.1131082,"died_in_gas":false,"last_in_flight":false,"last_is_parachuting":false,"last_is_dead":true},{"local_player":false,"ranking":9,"jump_position":[925.9275,3429.714],"jump_time":1633805169.039183,"touchdown_position":[1026.8334,3260.0],"touchdown_time":1633805175.8881924,"death_position":[1867.6666,1232.5],"death_time":1633805453.086542,"died_in_gas":false,"last_in_flight":false,"last_is_parachuting":false,"last_is_dead":true},{"local_player":false,"ranking":10,"jump_position":[1980.1805,2654.7478],"jump_time":1633805181.867338,"touchdown_position":[1514.1666,2290.5],"touchdown_time":1633805198.8141353,"death_position":[2226.1667,681.1667],"death_time":1633805450.9952462,"died_in_gas":false,"last_in_flight":false,"last_is_parachuting":false,"last_is_dead":true},{"local_player":false,"ranking":11,"jump_position":[898.60626,3449.7976],"jump_time":1633805168.7110133,"touchdown_position":[865.5,2719.8333],"touchdown_time":1633805181.4052794,"death_position":[1977.0,1437.5],"death_time":1633805443.317391,"died_in_gas":false,"last_in_flight":false,"last_is_parachuting":false,"last_is_dead":true},{"local_player":false,"ranking":12,"jump_position":[3143.6997,1799.4622],"jump_time":1633805196.0168917,"touchdown_position":[3184.1667,1504.5],"touchdown_time":1633805207.292458,"death_position":[2069.6274,1436.811],"death_time":1633805412.8079183,"died_in_gas":false,"last_in_flight":false,"last_is_parachuting":false,"last_is_dead":true},{"local_player":false,"ranking":13,"jump_position":[2482.7344,2285.3281],"jump_time":1633805187.9875336,"touchdown_position":[2873.5,2506.0],"touchdown_time":1633805204.9276903,"death_position":[2072.7024,1432.6499],"death_time":1633805411.4772184,"died_in_gas":false,"last_in_flight":false,"last_is_parachuting":false,"last_is_dead":true},{"local_player":false,"ranking":14,"jump_position":[2053.9246,2600.5393],"jump_time":1633805182.7723248,"touchdown_position":[2437.3333,1974.5],"touchdown_time":1633805195.4596734,"death_position":[1771.5159,1429.8506],"death_time":1633805408.1527946,"died_in_gas":false,"last_in_flight":false,"last_is_parachuting":false,"last_is_dead":true},{"local_player":false,"ranking":15,"jump_position":[1936.5339,2686.8318],"jump_time":1633805181.3417501,"touchdown_position":[2357.6667,2948.3333],"touchdown_time":1633805195.1297257,"death_position":[2060.9722,1537.7924],"death_time":1633805403.339497,"died_in_gas":false,"last_in_flight":false,"last_is_parachuting":false,"last_is_dead":true},{"local_player":false,"ranking":16,"jump_position":[3984.9355,1181.0822],"jump_time":1633805206.2626612,"touchdown_position":[3804.2825,1230.1017],"touchdown_time":1633805213.572706,"death_position":[2412.6125,602.59186],"death_time":1633805400.447549,"died_in_gas":false,"last_in_flight":false,"last_is_parachuting":false,"last_is_dead":true},{"local_player":false,"ranking":17,"jump_position":[923.18024,3431.7336],"jump_time":1633805169.0083582,"touchdown_position":[1293.8334,3698.8333],"touchdown_time":1633805183.19154,"death_position":[2137.3333,1893.1666],"death_time":1633805394.1692848,"died_in_gas":true,"last_in_flight":false,"last_is_parachuting":false,"last_is_dead":true},{"local_player":false,"ranking":18,"jump_position":[1081.5938,3315.2864],"jump_time":1633805170.926942,"touchdown_position":[1552.3334,3491.0],"touchdown_time":1633805184.2971976,"death_position":[2059.9006,1823.1348],"death_time":1633805391.670483,"died_in_gas":false,"last_in_flight":false,"last_is_parachuting":false,"last_is_dead":true},{"local_player":false,"ranking":19,"jump_position":[846.7236,3487.9358],"jump_time":1633805168.0788124,"touchdown_position":[1075.1666,3326.5],"touchdown_time":1633805177.2746685,"death_position":[1535.5,2279.8333],"death_time":1633805362.1931362,"died_in_gas":false,"last_in_flight":false,"last_is_parachuting":false,"last_is_dead":true},{"local_player":false,"ranking":20,"jump_position":[1428.4646,3060.3062],"jump_time":1633805175.1565297,"touchdown_position":[1585.8334,2153.3333],"touchdown_time":1633805192.1006794,"death_position":[2052.6118,1843.9056],"death_time":1633805354.0240564,"died_in_gas":false,"last_in_flight":false,"last_is_parachuting":false,"last_is_dead":true},{"local_player":false,"ranking":21,"jump_position":[4596.736,731.35895],"jump_time":1633805213.7414894,"touchdown_position":[4597.0,731.0],"touchdown_time":1633805230.6905465,"death_position":[4345.0,983.0],"death_time":1633805353.4574063,"died_in_gas":true,"last_in_flight":false,"last_is_parachuting":false,"last_is_dead":true},{"local_player":false,"ranking":22,"jump_position":[4596.736,731.35895],"jump_time":1633805213.741449,"touchdown_position":[4597.0,719.0],"touchdown_time":1633805230.6905172,"death_position":[4345.0,971.0],"death_time":1633805353.4573872,"died_in_gas":true,"last_in_flight":false,"last_is_parachuting":false,"last_is_dead":true},{"local_player":false,"ranking":23,"jump_position":[901.3302,3447.7952],"jump_time":1633805168.742277,"touchdown_position":[1421.3774,2395.1099],"touchdown_time":1633805185.6815958,"death_position":[1430.0,1621.5],"death_time":1633805353.1593697,"died_in_gas":false,"last_in_flight":false,"last_is_parachuting":false,"last_is_dead":true},{"local_player":false,"ranking":24,"jump_position":[3580.702,1478.2283],"jump_time":1633805201.3386054,"touchdown_position":[3103.8079,1075.7507],"touchdown_time":1633805214.896492,"death_position":[2651.5,566.5],"death_time":1633805344.3116975,"died_in_gas":false,"last_in_flight":false,"last_is_parachuting":false,"last_is_dead":true},{"local_player":false,"ranking":25,"jump_position":[1122.5626,3285.1707],"jump_time":1633805171.4275057,"touchdown_position":[1275.2858,2357.5684],"touchdown_time":1633805188.3811748,"death_position":[2191.6667,2080.8333],"death_time":1633805326.2301333,"died_in_gas":false,"last_in_flight":false,"last_is_parachuting":false,"last_is_dead":true},{"local_player":false,"ranking":26,"jump_position":[305.9565,3885.4465],"jump_time":1633805161.4929056,"touchdown_position":[522.1667,3340.3333],"touchdown_time":1633805175.5919945,"death_position":[2082.0,2152.8333],"death_time":1633805317.1920786,"died_in_gas":false,"last_in_flight":false,"last_is_parachuting":false,"last_is_dead":true},{"local_player":false,"ranking":27,"jump_position":[2698.6094,2126.6418],"jump_time":1633805190.6079895,"touchdown_position":[3064.8333,2359.5],"touchdown_time":1633805204.2387464,"death_position":[3270.3557,1538.713],"death_time":1633805310.2204623,"died_in_gas":false,"last_in_flight":false,"last_is_parachuting":false,"last_is_dead":true},{"local_player":false,"ranking":28,"jump_position":[906.7926,3443.78],"jump_time":1633805168.806688,"touchdown_position":[1291.6666,2889.8333],"touchdown_time":1633805181.0952232,"death_position":[1328.5,2763.8333],"death_time":1633805309.9205565,"died_in_gas":false,"last_in_flight":false,"last_is_parachuting":false,"last_is_dead":true},{"local_player":false,"ranking":29,"jump_position":[996.97015,3377.492],"jump_time":1633805169.9001322,"touchdown_position":[1034.261,3592.0437],"touchdown_time":1633805180.9085562,"death_position":[2146.5,2690.5],"death_time":1633805308.8802693,"died_in_gas":false,"last_in_flight":false,"last_is_parachuting":false,"last_is_dead":true},{"local_player":false,"ranking":30,"jump_position":[3307.5754,1678.9998],"jump_time":1633805198.0191727,"touchdown_position":[3271.1667,1582.1666],"touchdown_time":1633805211.738851,"death_position":[2860.8333,1434.5],"death_time":1633805302.7358055,"died_in_gas":false,"last_in_flight":false,"last_is_parachuting":false,"last_is_dead":true},{"local_player":false,"ranking":31,"jump_position":[2234.2231,2468.0056],"jump_time":1633805184.9522629,"touchdown_position":[2581.6667,2369.6667],"touchdown_time":1633805194.5353568,"death_position":[1270.1666,2544.8333],"death_time":1633805298.682611,"died_in_gas":false,"last_in_flight":false,"last_is_parachuting":false,"last_is_dead":true},{"local_player":false,"ranking":32,"jump_position":[1264.5885,3180.7688],"jump_time":1633805173.1617115,"touchdown_position":[1350.5,2723.3333],"touchdown_time":1633805183.024438,"death_position":[1228.5,2869.5],"death_time":1633805284.8320198,"died_in_gas":false,"last_in_flight":false,"last_is_parachuting":false,"last_is_dead":true},{"local_player":false,"ranking":33,"jump_position":[2171.3699,2514.2083],"jump_time":1633805184.1870077,"touchdown_position":[2387.0,2256.1667],"touchdown_time":1633805193.9270961,"death_position":[2937.8118,1490.7883],"death_time":1633805283.6933334,"died_in_gas":false,"last_in_flight":false,"last_is_parachuting":false,"last_is_dead":true},{"local_player":false,"ranking":34,"jump_position":[775.70404,3540.1423],"jump_time":1633805167.2169926,"touchdown_position":[1562.3334,3458.3333],"touchdown_time":1633805184.1556065,"death_position":[1404.0,3168.6667],"death_time":1633805280.066252,"died_in_gas":false,"last_in_flight":false,"last_is_parachuting":false,"last_is_dead":true},{"local_player":false,"ranking":35,"jump_position":[1958.3304,2670.8093],"jump_time":1633805181.6050234,"touchdown_position":[1908.8334,2495.5],"touchdown_time":1633805189.2057593,"death_position":[1799.6666,2364.5],"death_time":1633805277.6515617,"died_in_gas":false,"last_in_flight":false,"last_is_parachuting":false,"last_is_dead":true},{"local_player":false,"ranking":36,"jump_position":[325.06778,3871.3987],"jump_time":1633805161.7263925,"touchdown_position":[471.5,3944.3333],"touchdown_time":1633805168.7418306,"death_position":[1044.6666,3030.3333],"death_time":1633805269.8789132,"died_in_gas":false,"last_in_flight":false,"last_is_parachuting":false,"last_is_dead":true},{"local_player":false,"ranking":37,"jump_position":[431.55206,3793.1238],"jump_time":1633805163.0227306,"touchdown_position":[514.8333,3267.17],"touchdown_time":1633805173.2856717,"death_position":[1226.5,2974.5],"death_time":1633805267.5822396,"died_in_gas":false,"last_in_flight":false,"last_is_parachuting":false,"last_is_dead":true},{"local_player":false,"ranking":38,"jump_position":[1313.7517,3144.63],"jump_time":1633805173.7562625,"touchdown_position":[1337.1666,3346.8333],"touchdown_time":1633805190.7026858,"death_position":[1499.0988,3251.9636],"death_time":1633805264.2857153,"died_in_gas":false,"last_in_flight":false,"last_is_parachuting":false,"last_is_dead":true},{"local_player":false,"ranking":39,"jump_position":[2682.1165,2138.7656],"jump_time":1633805190.4011054,"touchdown_position":[2726.6667,1576.1666],"touchdown_time":1633805200.6506584,"death_position":[2492.6667,1271.1666],"death_time":1633805253.857407,"died_in_gas":false,"last_in_flight":false,"last_is_parachuting":false,"last_is_dead":true},{"local_player":false,"ranking":40,"jump_position":[1494.0151,3012.1208],"jump_time":1633805175.9513419,"touchdown_position":[1249.3334,2632.0],"touchdown_time":1633805185.916811,"death_position":[1387.6666,2880.5],"death_time":1633805253.0847156,"died_in_gas":false,"last_in_flight":false,"last_is_parachuting":false,"last_is_dead":true},{"local_player":false,"ranking":41,"jump_position":[2889.7249,1986.1555],"jump_time":1633805192.9295883,"touchdown_position":[3275.5,2216.6667],"touchdown_time":1633805207.229872,"death_position":[3284.6667,2118.3333],"death_time":1633805251.1180203,"died_in_gas":false,"last_in_flight":false,"last_is_parachuting":false,"last_is_dead":true},{"local_player":false,"ranking":42,"jump_position":[4148.866,1060.5801],"jump_time":1633805208.251929,"touchdown_position":[4038.0,1283.1666],"touchdown_time":1633805218.1973727,"death_position":[3313.1667,1490.8334],"death_time":1633805242.3858662,"died_in_gas":false,"last_in_flight":false,"last_is_parachuting":false,"last_is_dead":true},{"local_player":false,"ranking":43,"jump_position":[680.1065,3610.415],"jump_time":1633805166.0418322,"touchdown_position":[335.0,3545.3333],"touchdown_time":1633805174.8147864,"death_position":[1011.0225,3453.3582],"death_time":1633805241.4839203,"died_in_gas":false,"last_in_flight":false,"last_is_parachuting":false,"last_is_dead":true},{"local_player":false,"ranking":44,"jump_position":[355.07657,3849.3398],"jump_time":1633805162.087807,"touchdown_position":[683.0,4136.8335],"touchdown_time":1633805174.4849482,"death_position":[1085.1666,4108.8335],"death_time":1633805232.1168034,"died_in_gas":false,"last_in_flight":false,"last_is_parachuting":false,"last_is_dead":true},{"local_player":false,"ranking":45,"jump_position":[1657.9203,2891.6357],"jump_time":1633805177.9452837,"touchdown_position":[1712.6666,2785.1667],"touchdown_time":1633805185.0299976,"death_position":[1648.7734,2850.8538],"death_time":1633805220.736255,"died_in_gas":false,"last_in_flight":false,"last_is_parachuting":false,"last_is_dead":true},{"local_player":false,"ranking":46,"jump_position":[3487.9001,1546.4457],"jump_time":1633805200.2154608,"touchdown_position":[3638.0,1510.5],"touchdown_time":1633805209.5808291,"death_position":[3410.3333,1519.8334],"death_time":1633805220.0822146,"died_in_gas":false,"last_in_flight":false,"last_is_parachuting":false,"last_is_dead":true},{"local_player":false,"ranking":47,"jump_position":[1772.666,2807.2876],"jump_time":1633805179.3480105,"touchdown_position":[1523.3334,2725.6667],"touchdown_time":1633805190.543084,"death_position":[1501.8783,2754.7534],"death_time":1633805218.6283057,"died_in_gas":false,"last_in_flight":false,"last_is_parachuting":false,"last_is_dead":true},{"local_player":false,"ranking":48,"jump_position":[1780.8119,2801.2998],"jump_time":1633805179.4401257,"touchdown_position":[2358.8333,2907.1667],"touchdown_time":1633805193.894612,"death_position":[2471.3333,2925.8333],"death_time":1633805217.2218163,"died_in_gas":false,"last_in_flight":false,"last_is_parachuting":false,"last_is_dead":true},{"local_player":false,"ranking":49,"jump_position":[2286.1646,2429.8237],"jump_time":1633805185.5900078,"touchdown_position":[2365.0894,2676.3037],"touchdown_time":1633805198.550814,"death_position":[2439.0,2877.0],"death_time":1633805205.1583579,"died_in_gas":false,"last_in_flight":false,"last_is_parachuting":false,"last_is_dead":true},{"local_player":false,"ranking":50,"jump_position":[1663.3948,2887.6116],"jump_time":1633805178.0084813,"touchdown_position":[1800.0,2620.3333],"touchdown_time":1633805185.589757,"death_position":[1864.9476,2549.332],"death_time":1633805201.275981,"died_in_gas":false,"last_in_flight":false,"last_is_parachuting":false,"last_is_dead":true},{"local_player":false,"ranking":51,"jump_position":[1450.315,3044.2446],"jump_time":1633805175.4218085,"touchdown_position":[1462.6666,2800.8333],"touchdown_time":1633805183.3938873,"death_position":[1530.8334,2815.3333],"death_time":1633805200.45008,"died_in_gas":false,"last_in_flight":false,"last_is_parachuting":false,"last_is_dead":true},{"local_player":false,"ranking":52,"jump_position":[876.7845,3465.8384],"jump_time":1633805168.4463372,"touchdown_position":[969.0,3489.6667],"touchdown_time":1633805175.5165217,"death_position":[1127.3188,3434.785],"death_time":1633805199.7512069,"died_in_gas":false,"last_in_flight":false,"last_is_parachuting":false,"last_is_dead":true},{"local_player":false,"ranking":53,"jump_position":[1455.7773,3040.2292],"jump_time":1633805175.485685,"touchdown_position":[1406.8334,2885.8333],"touchdown_time":1633805183.3642077,"death_position":[1414.5,2875.0],"death_time":1633805198.9559546,"died_in_gas":false,"last_in_flight":false,"last_is_parachuting":false,"last_is_dead":true},{"local_player":false,"ranking":54,"jump_position":[1958.3304,2670.8093],"jump_time":1633805181.6048322,"touchdown_position":[1804.8334,2588.1667],"touchdown_time":1633805191.0425453,"death_position":[1804.8334,2588.1667],"death_time":1633805196.659074,"died_in_gas":false,"last_in_flight":false,"last_is_parachuting":false,"last_is_dead":true},{"local_player":false,"ranking":55,"jump_position":[1294.6338,3158.683],"jump_time":1633805173.5193608,"touchdown_position":[1177.6666,2532.1667],"touchdown_time":1633805185.68127,"death_position":[1151.9388,2515.2097],"death_time":1633805195.3962805,"died_in_gas":false,"last_in_flight":false,"last_is_parachuting":false,"last_is_dead":true},{"local_player":false,"ranking":56,"jump_position":[316.85495,3877.4355],"jump_time":1633805161.6328876,"touchdown_position":[604.3333,3975.1667],"touchdown_time":1633805170.8316493,"death_position":[911.6667,3791.1667],"death_time":1633805193.659535,"died_in_gas":false,"last_in_flight":false,"last_is_parachuting":false,"last_is_dead":true},{"local_player":false,"ranking":57,"jump_position":[641.85974,3638.5295],"jump_time":1633805165.5878532,"touchdown_position":[727.8333,2813.8333],"touchdown_time":1633805182.5368047,"death_position":[787.6667,2667.6667],"death_time":1633805193.5043218,"died_in_gas":false,"last_in_flight":false,"last_is_parachuting":false,"last_is_dead":true},{"local_player":false,"ranking":58,"jump_position":[314.18326,3879.3994],"jump_time":1633805161.603297,"touchdown_position":[526.6667,3691.8333],"touchdown_time":1633805168.6802568,"death_position":[595.0,3604.1667],"death_time":1633805193.4601023,"died_in_gas":false,"last_in_flight":false,"last_is_parachuting":false,"last_is_dead":true},{"local_player":false,"ranking":59,"jump_position":[267.6896,3913.576],"jump_time":1633805161.0274343,"touchdown_position":[395.83334,3687.5],"touchdown_time":1633805167.9393444,"death_position":[538.1667,3625.8333],"death_time":1633805189.3446789,"died_in_gas":false,"last_in_flight":false,"last_is_parachuting":false,"last_is_dead":true},{"local_player":false,"ranking":60,"jump_position":[756.58124,3554.1992],"jump_time":1633805166.9801383,"touchdown_position":[642.0,3531.0],"touchdown_time":1633805175.0813048,"death_position":[642.0,3525.0],"death_time":1633805180.643174,"died_in_gas":false,"last_in_flight":false,"last_is_parachuting":false,"last_is_dead":true},{"local_player":false,"ranking":61,"jump_position":[297.71997,3891.5012],"jump_time":1633805161.4025364,"touchdown_position":[484.8656,4018.467],"touchdown_time":1633805169.6006784,"death_position":[512.8333,4060.1667],"death_time":1633805178.4422905,"died_in_gas":false,"last_in_flight":false,"last_is_parachuting":false,"last_is_dead":true},{"local_player":false,"ranking":62,"jump_position":[570.8468,3690.73],"jump_time":1633805164.713528,"touchdown_position":[625.3333,3655.8333],"touchdown_time":1633805173.7232442,"death_position":[625.3333,3655.8333],"death_time":1633805176.916236,"died_in_gas":false,"last_in_flight":false,"last_is_parachuting":false,"last_is_dead":true},{"local_player":false,"ranking":63,"jump_position":[518.9528,3728.8765],"jump_time":1633805164.0885746,"touchdown_position":[587.04156,3707.4678],"touchdown_time":1633805172.8968613,"death_position":[587.1764,3699.5083],"death_time":1633805175.220887,"died_in_gas":false,"last_in_flight":false,"last_is_parachuting":false,"last_is_dead":true}],"local_player_info":{"local_player":true,"ranking":0,"jump_position":[4596.736,731.35895],"jump_time":1633805213.741375,"touchdown_position":[4597.0,665.062],"touchdown_time":1633805230.6904397,"death_position":[4345.0,917.3221],"death_time":1633805353.4573393,"died_in_gas":true,"last_in_flight":false,"last_is_parachuting":false,"last_is_dead":true}}