{"version":3,"start_time":1633781430.0813582,"game_started":true,"end_time":1633781820.5964663,"game_ended":true,"flight_start":[3751.2205,11.0],"flight_end":[1797.7203,4597.0],"last_gas_center":[3672.33,1363.0636],"last_gas_radius":40.114098,"players":[{"local_player":false,"ranking":1,"jump_position":[1797.7203,4597.0],"jump_time":1633781478.965141,"touchdown_position":[1545.8334,4184.3335],"touchdown_time":1633781495.917266,"death_position":[0.0,0.0],"death_time":0.0,"died_in_gas":false,"last_in_flight":false,"last_is_parachuting":false,"last_is_dead":false},{"local_player":false,"ranking":2,"jump_position":[1797.7203,4597.0],"jump_time":1633781478.965353,"touchdown_position":[1860.3801,4167.0444],"touchdown_time":1633781489.068537,"death_position":[3675.3442,1363.2202],"death_time":1633781820.5810752,"died_in_gas":false,"last_in_flight":false,"last_is_parachuting":false,"last_is_dead":true},{"local_player":false,"ranking":3,"jump_position":[3508.129,581.68225],"jump_time":1633781436.1688232,"touchdown_position":[2835.5,576.6667],"touchdown_time":1633781453.113088,"death_position":[3681.1667,1453.8334],"death_time":1633781810.1082745,"died_in_gas":true,"last_in_flight":false,"last_is_parachuting":false,"last_is_dead":true},{"local_player":false,"ranking":4,"jump_position":[2994.0132,1788.6188],"jump_time":1633781449.028909,"touchdown_position":[3395.0,1999.1666],"touchdown_time":1633781465.9696968,"death_position":[3642.2366,1428.2933],"death_time":1633781808.1171088,"died_in_gas":false,"last_in_flight":false,"last_is_parachuting":false,"last_is_dead":true},{"local_player":false,"ranking":5,"jump_position":[2353.6934,3291.818],"jump_time":1633781465.0456827,"touchdown_position":[1912.6666,3655.1667],"touchdown_time":1633781477.2704153,"death_position":[3701.4949,1473.1721],"death_time":1633781774.659127,"died_in_gas":false,"last_in_flight":false,"last_is_parachuting":false,"last_is_dead":true},{"local_player":false,"ranking":6,"jump_position":[3622.376,313.47668],"jump_time":1633781433.305605,"touchdown_position":[3410.3333,363.83334],"touchdown_time":1633781442.6798608,"death_position":[3518.1667,1356.5],"death_time":1633781772.556932,"died_in_gas":false,"last_in_flight":false,"last_is_parachuting":false,"last_is_dead":true},{"local_player":false,"ranking":7,"jump_position":[2582.1934,2755.3965],"jump_time":1633781459.3281658,"touchdown_position":[2060.5,2728.5],"touchdown_time":1633781476.3391702,"death_position":[3656.961,1691.2501],"death_time":1633781764.184129,"died_in_gas":false,"last_in_flight":false,"last_is_parachuting":false,"last_is_dead":true},{"local_player":false,"ranking":8,"jump_position":[3439.043,743.8695],"jump_time":1633781437.8869514,"touchdown_position":[3680.6667,1173.3334],"touchdown_time":1633781452.2758212,"death_position":[3536.1663,1317.0773],"death_time":1633781744.1485403,"died_in_gas":false,"last_in_flight":false,"last_is_parachuting":false,"last_is_dead":true},{"local_player":false,"ranking":9,"jump_position":[2562.2795,2802.1448],"jump_time":1633781459.8283415,"touchdown_position":[2469.5,2953.6667],"touchdown_time":1633781467.933775,"death_position":[3515.8333,1335.5],"death_time":1633781720.444582,"died_in_gas":false,"last_in_flight":false,"last_is_parachuting":false,"last_is_dead":true},{"local_player":false,"ranking":10,"jump_position":[3044.5083,1670.0767],"jump_time":1633781447.7665365,"touchdown_position":[2666.343,1941.3928],"touchdown_time":1633781459.3574908,"death_position":[3649.1667,1896.1666],"death_time":1633781718.8179624,"died_in_gas":false,"last_in_flight":false,"last_is_parachuting":false,"last_is_dead":true},{"local_player":false,"ranking":11,"jump_position":[2644.6309,2608.8215],"jump_time":1633781457.7727616,"touchdown_position":[2298.1667,2601.3333],"touchdown_time":1633781467.0345738,"death_position":[3523.923,1665.8334],"death_time":1633781711.271932,"died_in_gas":false,"last_in_flight":false,"last_is_parachuting":false,"last_is_dead":true},{"local_player":false,"ranking":12,"jump_position":[3437.7278,746.95715],"jump_time":1633781437.932046,"touchdown_position":[2996.0,801.0],"touchdown_time":1633781450.2586133,"death_position":[3328.8809,1670.4797],"death_time":1633781707.9575467,"died_in_gas":false,"last_in_flight":false,"last_is_parachuting":false,"last_is_dead":true},{"local_player":false,"ranking":13,"jump_position":[3219.863,1258.4153],"jump_time":1633781443.3795836,"touchdown_position":[3006.0,1202.8334],"touchdown_time":1633781454.8120916,"death_position":[3390.8333,1495.0],"death_time":1633781691.2070146,"died_in_gas":false,"last_in_flight":false,"last_is_parachuting":false,"last_is_dead":true},{"local_player":false,"ranking":14,"jump_position":[3071.0747,1607.7097],"jump_time":1633781447.0993981,"touchdown_position":[3218.8333,1809.1666],"touchdown_time":1633781464.0454779,"death_position":[3778.8333,1952.6666],"death_time":1633781682.0959666,"died_in_gas":false,"last_in_flight":false,"last_is_parachuting":false,"last_is_dead":true},{"local_player":false,"ranking":15,"jump_position":[3543.982,497.51257],"jump_time":1633781435.2733023,"touchdown_position":[3483.3333,595.0],"touchdown_time":1633781442.4785495,"death_position":[3725.8333,1479.3334],"death_time":1633781669.2455115,"died_in_gas":false,"last_in_flight":false,"last_is_parachuting":false,"last_is_dead":true},{"local_player":false,"ranking":16,"jump_position":[3510.76,575.50543],"jump_time":1633781436.1068008,"touchdown_position":[3810.3333,850.3333],"touchdown_time":1633781447.969693,"death_position":[3717.8333,1531.8334],"death_time":1633781661.6533747,"died_in_gas":false,"last_in_flight":false,"last_is_parachuting":false,"last_is_dead":true},{"local_player":false,"ranking":17,"jump_position":[2940.8892,1913.3309],"jump_time":1633781450.3532307,"touchdown_position":[2755.1667,1728.5],"touchdown_time":1633781467.2993608,"death_position":[2993.1033,1575.8514],"death_time":1633781650.0541961,"died_in_gas":false,"last_in_flight":false,"last_is_parachuting":false,"last_is_dead":true},{"local_player":false,"ranking":18,"jump_position":[3598.4346,369.67984],"jump_time":1633781433.902104,"touchdown_position":[3144.1667,856.0],"touchdown_time":1633781450.8553164,"death_position":[3133.3384,1438.394],"death_time":1633781634.597642,"died_in_gas":false,"last_in_flight":false,"last_is_parachuting":false,"last_is_dead":true},{"local_player":false,"ranking":19,"jump_position":[3536.0315,516.1772],"jump_time":1633781435.464056,"touchdown_position":[4087.0,664.6667],"touchdown_time":1633781448.094667,"death_position":[3350.0,1254.0],"death_time":1633781622.9989214,"died_in_gas":false,"last_in_flight":false,"last_is_parachuting":false,"last_is_dead":true},{"local_player":false,"ranking":20,"jump_position":[3389.904,859.22864],"jump_time":1633781439.1189964,"touchdown_position":[3919.7727,1423.805],"touchdown_time":1633781456.070122,"death_position":[3760.3333,2370.6667],"death_time":1633781617.587829,"died_in_gas":false,"last_in_flight":false,"last_is_parachuting":false,"last_is_dead":true},{"local_player":false,"ranking":21,"jump_position":[1935.2349,4274.1772],"jump_time":1633781475.5162618,"touchdown_position":[2118.0,3981.0],"touchdown_time":1633781485.9788215,"death_position":[3013.8333,2110.6667],"death_time":1633781617.2572029,"died_in_gas":false,"last_in_flight":false,"last_is_parachuting":false,"last_is_dead":true},{"local_player":false,"ranking":22,"jump_position":[2353.6934,3291.818],"jump_time":1633781465.046512,"touchdown_position":[2268.8333,3056.5],"touchdown_time":1633781478.533273,"death_position":[2370.9065,1606.4419],"death_time":1633781611.0714378,"died_in_gas":false,"last_in_flight":false,"last_is_parachuting":false,"last_is_dead":true},{"local_player":false,"ranking":23,"jump_position":[2198.2512,3656.731],"jump_time":1633781468.9280171,"touchdown_position":[2279.8643,3744.1907],"touchdown_time":1633781480.657818,"death_position":[2371.3333,1670.6666],"death_time":1633781604.057615,"died_in_gas":false,"last_in_flight":false,"last_is_parachuting":false,"last_is_dead":true},{"local_player":false,"ranking":24,"jump_position":[2920.9626,1960.1106],"jump_time":1633781450.8554037,"touchdown_position":[2441.6667,1852.5],"touchdown_time":1633781467.7967644,"death_position":[2488.5,2472.8333],"death_time":1633781593.4864671,"died_in_gas":false,"last_in_flight":false,"last_is_parachuting":false,"last_is_dead":true},{"local_player":false,"ranking":25,"jump_position":[3589.1692,391.43146],"jump_time":1633781434.1380525,"touchdown_position":[3511.6667,369.83334],"touchdown_time":1633781442.913088,"death_position":[3194.8333,1222.8334],"death_time":1633781586.309563,"died_in_gas":false,"last_in_flight":false,"last_is_parachuting":false,"last_is_dead":true},{"local_player":false,"ranking":26,"jump_position":[3122.8867,1486.0767],"jump_time":1633781445.802858,"touchdown_position":[3034.3333,1287.6666],"touchdown_time":1633781459.329139,"death_position":[2935.0266,1985.9777],"death_time":1633781583.5871737,"died_in_gas":false,"last_in_flight":false,"last_is_parachuting":false,"last_is_dead":true},{"local_player":false,"ranking":27,"jump_position":[2620.7207,2664.9512],"jump_time":1633781458.3651466,"touchdown_position":[2551.0,2406.5],"touchdown_time":1633781467.375492,"death_position":[3292.445,2087.1558],"death_time":1633781567.0349076,"died_in_gas":false,"last_in_flight":false,"last_is_parachuting":false,"last_is_dead":true},{"local_player":false,"ranking":28,"jump_position":[3613.0815,335.2958],"jump_time":1633781433.5399747,"touchdown_position":[3507.1667,313.66666],"touchdown_time":1633781440.9106977,"death_position":[3931.5227,2120.9553],"death_time":1633781546.326417,"died_in_gas":false,"last_in_flight":false,"last_is_parachuting":false,"last_is_dead":true},{"local_player":false,"ranking":29,"jump_position":[2085.3643,3921.7375],"jump_time":1633781471.762822,"touchdown_position":[1983.1666,3874.0],"touchdown_time":1633781478.576542,"death_position":[2446.9282,3867.579],"death_time":1633781546.2617824,"died_in_gas":false,"last_in_flight":false,"last_is_parachuting":false,"last_is_dead":true},{"local_player":false,"ranking":30,"jump_position":[2203.598,3644.179],"jump_time":1633781468.8018813,"touchdown_position":[2061.0,3576.6667],"touchdown_time":1633781477.801285,"death_position":[2680.5,2129.1667],"death_time":1633781541.0434835,"died_in_gas":false,"last_in_flight":false,"last_is_parachuting":false,"last_is_dead":true},{"local_player":false,"ranking":31,"jump_position":[3443.0227,734.52655],"jump_time":1633781437.7912512,"touchdown_position":[3295.5,725.5],"touchdown_time":1633781445.008978,"death_position":[2724.4055,905.92773],"death_time":1633781535.262428,"died_in_gas":false,"last_in_flight":false,"last_is_parachuting":false,"last_is_dead":true},{"local_player":false,"ranking":32,"jump_position":[3245.1033,1199.1609],"jump_time":1633781442.741986,"touchdown_position":[3361.8333,1191.6666],"touchdown_time":1633781451.0897915,"death_position":[3103.1667,828.6667],"death_time":1633781533.5638585,"died_in_gas":false,"last_in_flight":false,"last_is_parachuting":false,"last_is_dead":true},{"local_player":false,"ranking":33,"jump_position":[3315.4775,1033.9525],"jump_time":1633781440.9863827,"touchdown_position":[2633.9397,1449.7351],"touchdown_time":1633781457.9292364,"death_position":[2858.537,1654.023],"death_time":1633781532.2121873,"died_in_gas":false,"last_in_flight":false,"last_is_parachuting":false,"last_is_dead":true},{"local_player":false,"ranking":34,"jump_position":[3594.483,378.95673],"jump_time":1633781434.0102308,"touchdown_position":[3462.1667,725.3333],"touchdown_time":1633781447.0677614,"death_position":[2999.1667,619.1667],"death_time":1633781530.6451533,"died_in_gas":false,"last_in_flight":false,"last_is_parachuting":false,"last_is_dead":true},{"local_player":false,"ranking":35,"jump_position":[3615.7385,329.0585],"jump_time":1633781433.477119,"touchdown_position":[3025.7456,531.56177],"touchdown_time":1633781447.5644374,"death_position":[2565.0789,555.48376],"death_time":1633781525.9882114,"died_in_gas":false,"last_in_flight":false,"last_is_parachuting":false,"last_is_dead":true},{"local_player":false,"ranking":36,"jump_position":[3207.9065,1286.4849],"jump_time":1633781443.6709263,"touchdown_position":[2957.0,1316.5],"touchdown_time":1633781453.1133258,"death_position":[2689.5,1344.1666],"death_time":1633781521.7109725,"died_in_gas":false,"last_in_flight":false,"last_is_parachuting":false,"last_is_dead":true},{"local_player":false,"ranking":37,"jump_position":[2608.776,2692.9924],"jump_time":1633781458.6620243,"touchdown_position":[2785.5,2612.5],"touchdown_time":1633781472.5912433,"death_position":[2784.5,1908.3334],"death_time":1633781519.145511,"died_in_gas":false,"last_in_flight":false,"last_is_parachuting":false,"last_is_dead":true},{"local_player":false,"ranking":38,"jump_position":[2805.2344,2231.7756],"jump_time":1633781453.7768483,"touchdown_position":[2949.0,2093.5],"touchdown_time":1633781463.043163,"death_position":[2880.3333,1314.0],"death_time":1633781510.9113345,"died_in_gas":false,"last_in_flight":false,"last_is_parachuting":false,"last_is_dead":true},{"local_player":false,"ranking":39,"jump_position":[2531.7104,2873.9087],"jump_time":1633781460.5908644,"touchdown_position":[1997.8334,2902.3333],"touchdown_time":1633781471.9202857,"death_position":[1455.1061,2790.9],"death_time":1633781505.4508038,"died_in_gas":false,"last_in_flight":false,"last_is_parachuting":false,"last_is_dead":true},{"local_player":false,"ranking":40,"jump_position":[3195.9512,1314.5508],"jump_time":1633781443.968872,"touchdown_position":[3280.0,1749.8334],"touchdown_time":1633781457.336064,"death_position":[3560.6099,1821.811],"death_time":1633781503.461298,"died_in_gas":false,"last_in_flight":false,"last_is_parachuting":false,"last_is_dead":true},{"local_player":false,"ranking":41,"jump_position":[3429.757,765.6692],"jump_time":1633781438.118909,"touchdown_position":[3800.3333,1119.0],"touchdown_time":1633781453.3166063,"death_position":[4206.1665,1346.3334],"death_time":1633781499.9376514,"died_in_gas":false,"last_in_flight":false,"last_is_parachuting":false,"last_is_dead":true},{"local_player":false,"ranking":42,"jump_position":[2147.7878,3775.1956],"jump_time":1633781470.2001212,"touchdown_position":[2153.5,3931.5],"touchdown_time":1633781478.9652624,"death_position":[2194.0,3710.1667],"death_time":1633781499.339192,"died_in_gas":false,"last_in_flight":false,"last_is_parachuting":false,"last_is_dead":true},{"local_player":false,"ranking":43,"jump_position":[2878.447,2059.919],"jump_time":1633781451.9193127,"touchdown_position":[2258.3333,1895.3334],"touchdown_time":1633781468.8656094,"death_position":[2011.6666,1398.6666],"death_time":1633781499.2455094,"died_in_gas":false,"last_in_flight":false,"last_is_parachuting":false,"last_is_dead":true},{"local_player":false,"ranking":44,"jump_position":[2951.5005,1888.42],"jump_time":1633781450.08636,"touchdown_position":[3168.0,1485.0],"touchdown_time":1633781462.6242232,"death_position":[2941.0,1294.1666],"death_time":1633781497.7081852,"died_in_gas":false,"last_in_flight":false,"last_is_parachuting":false,"last_is_dead":true},{"local_player":false,"ranking":45,"jump_position":[3138.8281,1448.6527],"jump_time":1633781445.398889,"touchdown_position":[2733.1985,1201.2689],"touchdown_time":1633781460.2951775,"death_position":[2067.8333,915.1667],"death_time":1633781495.8058128,"died_in_gas":false,"last_in_flight":false,"last_is_parachuting":false,"last_is_dead":true},{"local_player":false,"ranking":46,"jump_position":[2054.8062,3993.4758],"jump_time":1633781472.5288427,"touchdown_position":[2155.6667,3910.5],"touchdown_time":1633781480.565556,"death_position":[2182.0,3940.3333],"death_time":1633781489.4410028,"died_in_gas":false,"last_in_flight":false,"last_is_parachuting":false,"last_is_dead":true},{"local_player":false,"ranking":47,"jump_position":[2546.3384,2839.5686],"jump_time":1633781460.2330902,"touchdown_position":[2466.0,2991.0],"touchdown_time":1633781471.058913,"death_position":[2517.444,2883.8594],"death_time":1633781487.775514,"died_in_gas":false,"last_in_flight":false,"last_is_parachuting":false,"last_is_dead":true},{"local_player":false,"ranking":48,"jump_position":[2050.8171,4002.84],"jump_time":1633781472.6225612,"touchdown_position":[2095.0,3969.6667],"touchdown_time":1633781480.6581395,"death_position":[2154.0,3965.2952],"death_time":1633781487.5754223,"died_in_gas":false,"last_in_flight":false,"last_is_parachuting":false,"last_is_dead":true},{"local_player":false,"ranking":49,"jump_position":[3237.1257,1217.8888],"jump_time":1633781442.9463696,"touchdown_position":[3318.0,1241.0],"touchdown_time":1633781457.8370078,"death_position":[3525.575,1415.4575],"death_time":1633781483.8854222,"died_in_gas":false,"last_in_flight":false,"last_is_parachuting":false,"last_is_dead":true},{"local_player":false,"ranking":50,"jump_position":[2436.0747,3098.4211],"jump_time":1633781462.9828165,"touchdown_position":[2127.0,3048.0],"touchdown_time":1633781472.7944741,"death_position":[2134.2861,3031.4104],"death_time":1633781482.4293451,"died_in_gas":false,"last_in_flight":false,"last_is_parachuting":false,"last_is_dead":true},{"local_player":false,"ranking":51,"jump_position":[2966.1296,1854.0768],"jump_time":1633781449.7306716,"touchdown_position":[2576.8333,2013.3334],"touchdown_time":1633781460.8564892,"death_position":[2575.996,2009.345],"death_time":1633781475.0784278,"died_in_gas":false,"last_in_flight":false,"last_is_parachuting":false,"last_is_dead":true},{"local_player":false,"ranking":52,"jump_position":[2429.4348,3114.0093],"jump_time":1633781463.1539905,"touchdown_position":[2498.0,3074.3333],"touchdown_time":1633781470.7612734,"death_position":[2496.0,3045.0],"death_time":1633781472.221861,"died_in_gas":false,"last_in_flight":false,"last_is_parachuting":false,"last_is_dead":true},{"local_player":false,"ranking":53,"jump_position":[2487.885,2976.7927],"jump_time":1633781461.6812916,"touchdown_position":[2507.0,2924.5],"touchdown_time":1633781469.267092,"death_position":[2505.0,2919.0],"death_time":1633781471.2935543,"died_in_gas":false,"last_in_flight":false,"last_is_parachuting":false,"last_is_dead":true},{"local_player":false,"ranking":54,"jump_position":[3348.6936,955.9742],"jump_time":1633781440.1507392,"touchdown_position":[3451.8333,1232.3334],"touchdown_time":1633781452.0433984,"death_position":[3340.6667,1273.3334],"death_time":1633781470.825466,"died_in_gas":false,"last_in_flight":false,"last_is_parachuting":false,"last_is_dead":true},{"local_player":false,"ranking":55,"jump_position":[2713.725,2446.6194],"jump_time":1633781456.038423,"touchdown_position":[2573.5,2419.5],"touchdown_time":1633781462.9505498,"death_position":[2572.5,2410.5],"death_time":1633781470.4351847,"died_in_gas":false,"last_in_flight":false,"last_is_parachuting":false,"last_is_dead":true},{"local_player":false,"ranking":56,"jump_position":[3124.2153,1482.9579],"jump_time":1633781445.7700646,"touchdown_position":[2781.8645,1449.6194],"touchdown_time":1633781454.341132,"death_position":[2792.4465,1434.9373],"death_time":1633781470.2319098,"died_in_gas":false,"last_in_flight":false,"last_is_parachuting":false,"last_is_dead":true},{"local_player":false,"ranking":57,"jump_position":[3603.777,357.1383],"jump_time":1633781433.7744508,"touchdown_position":[3526.6667,553.6667],"touchdown_time":1633781442.0090535,"death_position":[3420.0,628.1667],"death_time":1633781463.4509847,"died_in_gas":false,"last_in_flight":false,"last_is_parachuting":false,"last_is_dead":true},{"local_player":false,"ranking":58,"jump_position":[3416.473,796.8555],"jump_time":1633781438.4604294,"touchdown_position":[3021.0,844.8333],"touchdown_time":1633781449.1533673,"death_position":[3021.0,816.0],"death_time":1633781459.999833,"died_in_gas":false,"last_in_flight":false,"last_is_parachuting":false,"last_is_dead":true},{"local_player":false,"ranking":59,"jump_position":[3547.9873,488.10947],"jump_time":1633781435.1665802,"touchdown_position":[3097.3333,1250.5],"touchdown_time":1633781452.1867201,"death_position":[2994.0,1318.3334],"death_time":1633781458.3646674,"died_in_gas":false,"last_in_flight":false,"last_is_parachuting":false,"last_is_dead":true},{"local_player":false,"ranking":60,"jump_position":[3242.4402,1205.4124],"jump_time":1633781442.8213367,"touchdown_position":[3243.0,1179.0],"touchdown_time":1633781450.2588372,"death_position":[3249.6667,1159.1666],"death_time":1633781456.1004593,"died_in_gas":false,"last_in_flight":false,"last_is_parachuting":false,"last_is_dead":true},{"local_player":false,"ranking":61,"jump_position":[3623.6917,310.38824],"jump_time":1633781433.2769647,"touchdown_position":[3016.3333,705.6667],"touchdown_time":1633781448.1572301,"death_position":[2981.6667,717.1667],"death_time":1633781454.4710083,"died_in_gas":false,"last_in_flight":false,"last_is_parachuting":false,"last_is_dead":true},{"local_player":false,"ranking":62,"jump_position":[3298.2322,1074.4377],"jump_time":1633781441.4201465,"touchdown_position":[3087.0,780.0],"touchdown_time":1633781451.591173,"death_position":[3087.0,780.0],"death_time":1633781453.4763236,"died_in_gas":false,"last_in_flight":false,"last_is_parachuting":false,"last_is_dead":true},{"local_player":false,"ranking":63,"jump_position":[3585.1707,400.81845],"jump_time":1633781434.243544,"touchdown_position":[3236.3333,319.83334],"touchdown_time":1633781443.0846138,"death_position":[3236.3333,319.83334],"death_time":1633781452.9422379,"died_in_gas":false,"last_in_flight":false,"last_is_parachuting":false,"last_is_dead":true}],"local_player_info":{"local_player":true,"ranking":0,"jump_position":[1797.7203,4597.0],"jump_time":1633781478.9650803,"touchdown_position":[1797.7203,4530.919],"touchdown_time":1633781495.917106,"death_position":[1797.7203,4198.178],"death_time":1633781623.438604,"died_in_gas":true,"last_in_flight":false,"last_is_parachuting":false,"last_is_dead":true}}